pypods/__init__.py
pypods/errors.py
pypods/ns.py
pypods/pods.py
pypods/template/pod.py
pypods-0.2.0.dist-info/LICENSE
pypods-0.2.0.dist-info/METADATA
pypods-0.2.0.dist-info/WHEEL
pypods-0.2.0.dist-info/top_level.txt
pypods-0.2.0.dist-info/RECORD
