Metadata-Version: 2.1
Name: pypods
Version: 0.2.0
Summary: A lightweight solution to execute Python dependencies in an isolated fashion.
Home-page: https://github.com/Rohan2002/pypods
Author: Rohan Deshpande
Author-email: rohandeshpande832@gmail.com
License: UNKNOWN
Platform: UNKNOWN
Classifier: Programming Language :: Python :: 3
Classifier: License :: OSI Approved :: MIT License
Classifier: Operating System :: OS Independent
Requires-Python: >=3.6
License-File: LICENSE
Requires-Dist: bson
